{
  "titolo": "Status dei non musulmani nel diritto islamico e tutela della libertà religiosa nell'ordinamento italiano",
  "bozza": false,
  "stato": "passato",
  "dataInizio": "2026-04-25T14:30",
  "tuttoIlGiorno": false,
  "luogo": {
    "nome": "Moschea Al Huda",
    "indirizzo": "via dei frassini, 4 ",
    "citta": "Roma"
  },
  "copertina": "/images/eventi/status-dei-non-musulmani-nel-diritto-islamico-e-tutela-della-liberta-religiosa-nell-ordinamento-italiano/copertina.png",
  "ctaEsterna": {},
  "inEvidenza": false,
  "descrizione": "Assalamu è aleykum, vi aspettiamo il 25 aprile alle ore 14:30 presso la moschea Al Huda (via dei Frassini 4) per un incontro aperto a tutti.\nParleremo del rapporto tra Islam e non musulmani e della libertà religiosa nei Paesi musulmani.\nAnalizzeremo anche l’ordinamento italiano per capire come è tutelata la libertà di culto e quali difficoltà esistono.",
  "seo": {},
  "traduzioni": {
    "en": {},
    "ar": {},
    "bn": {}
  }
}
